liteconfig/__init__.py
liteconfig/liteconfig.py
tests/__init__.py
tests/test-liteconfig.py
liteconfig-0.1.2.dist-info/LICENSE
liteconfig-0.1.2.dist-info/METADATA
liteconfig-0.1.2.dist-info/WHEEL
liteconfig-0.1.2.dist-info/top_level.txt
liteconfig-0.1.2.dist-info/RECORD
