Metadata-Version: 2.1
Name: liteconfig
Version: 0.1.2
Summary: Lightweight and configurable .ini config parser with dot notation property access.
Home-page: https://github.com/zmej-serow/liteconfig
Author: Zmej Serow
Author-email: zmej.serow@gmail.com
License: MIT
Keywords: configparser ini parsing conf cfg configuration file
Platform: any
Classifier: Programming Language :: Python
Classifier: Programming Language :: Python :: 3
Classifier: Intended Audience :: Developers
Classifier: License :: OSI Approved :: MIT License
Classifier: Operating System :: OS Independent
Classifier: Topic :: Software Development :: Libraries
Classifier: Topic :: Software Development :: Libraries :: Python Modules
